{
  "1": "0KMGf0ebdR8aazf1PoHEdb",
  "2": "5L8ta4ECl5zeA6bGqY7G38",
  "3": "0wAyDBh0ujohCsYeXBtDLF",
  "4": "5E4leLVW7JFBMXZqP2C2aS",
  "6": "6GYqOflskcZxPj8rkTZkOy",
  "8": "2xar08Fq5xra2KKZs5Bw9j",
  "9": "1uRKT2LRANv4baowBWHfDS",
  "10": "4ZfQwNx3FlCN07cnUvekh3",
  "11": "0S8ibKBl3tjRmYbZhGHNhG",
  "12": "2iXcvnD3d1gfLBum0cE5Eg",
  "14": "0TMrV95mP7sDlvbE4iVfKP",
  "15": "1s4hyUFWmLWiAamsclb4xA",
  "17": "4gphxUgq0JSFv2BCLhNDiE",
  "18": "39lnzOIUCSNaQmgBHoz7rt",
  "19": "5gJKsGij5oGt5H5RSFYXPa",
  "20": "3oAWTk92mZBxKBOKf8mR5v",
  "21": "6CdqdbrXCFWbhpVwaNMzpv",
  "22": "32fZXsDwoDchpdtsCmeo0o",
  "24": "2aEeghgUcnu75tzcolFMfs",
  "25": "2QfiRTz5Yc8DdShCxG1tB2",
  "26": "1KLpjQFgubHI3GkAICCNH3",
  "27": "1FmhMxnbJ1wGQ2gARKK79C",
  "28": "4YCnTYbq3oL1Lqpyxg33CU",
  "29": "4aTCNddtjztjuK2EOgz7ZZ",
  "30": "4x7OshbFaXR0hlWK03QmNI",
  "31": "0uxu2GzsOMGNZ7C1ul84Mf",
  "32": "1UwriLz98ILbRhrtohTca1",
  "34": "1INWPr855fwWdAOeecbu0W",
  "37": "7utoClKnLShFg6u6dZ20gp",
  "38": "5xzdDMhFYiuUONB0Mha9VS",
  "39": "6YffUZJ2R06kyxyK6onezL",
  "40": "1Pq47iFLC5U7j8xeNiNcuS",
  "41": "4kOO2ADjyM5oJxcUiPsG15",
  "42": "2dbaIpJoAk2hhrrX2ljKJo",
  "43": "48i055G1OT5KxGGftwFxWy",
  "45": "6InPZ10jEoMFI0ZuY0AMMx",
  "46": "35hfuechuOqaW31ogdauO7",
  "47": "48ZjHLkaHpXIlGGYUlb3bZ",
  "48": "5eQCkMjULSswZ5rI2jGpk0",
  "49": "2qhASBzpbFhPRtrnZ5lLnz",
  "51": "0BbA7S30mOQB94e4IBnqCt",
  "52": "1GY8zOFi8rC39xXnD0tKO8",
  "53": "5haXbSJqjjM0TCJ5XkfEaC",
  "54": "2PzU4IB8Dr6mxV3lHuaG34",
  "56": "4SGBuq37Ol4HJr7pQqFMKa",
  "58": "6b6IMqP565TbtFFZg9iFf3",
  "61": "3G7tRC24Uh09Hmp1KZ7LQ2",
  "62": "2mTiKaGdMPA4wfOGGUroE5",
  "64": "3YJx77Xx8JSwEoxqrkQO5c",
  "65": "1BmVQ5RGqqtF5cnsv6cQYu",
  "66": "6vcNJUWtUPB0hKC6VbZriY",
  "67": "1JO1xLtVc8mWhIoE3YaCL0",
  "68": "0S1nTYJUNSKpuJkkG4gucV",
  "69": "6RJK553YhstRzyKA4mug09",
  "70": "63OFKbMaZSDZ4wtesuuq6f",
  "71": "0YZ3J8xzGwLOg4yEgST1YK",
  "73": "6hleUCx3E4gB2urwRvx1QT",
  "75": "6sPOmDulFtLzfX25zICNrC",
  "76": "6H3Wa6hWR9DRMzMSd4pZkT",
  "77": "2EqlS6tkEnglzr7tkKAAYD",
  "78": "6pxWv6GV35VGmcPf5dh6CH",
  "81": "6vR3EeRjcUf7ad98I4Euds",
  "82": "1d5Q5obZOAyTECARxbBkVy",
  "83": "6MTd61g9zq6CB1FnJydjEb",
  "84": "38zsOOcu31XbbYj9BIPUF1",
  "86": "36gPq8WG7tDxrblyGVUCiT",
  "87": "2eF8pWbiivYsYRpbntYsnc",
  "88": "6IwTuQuQ4suJTQ43plwZef",
  "89": "7jhKkbM3KZvnuqzMX5fADH",
  "90": "0MHXrqn909p0LRTPsNsGEi",
  "92": "3ZE3wv8V3w2T2f7nOCjV0N",
  "93": "0DcrhZ12WcCqruCs8ibXSf",
  "95": "0pjgcw5stw4SEZ3cryVuZh",
  "97": "1GyQrKyK660LcFW1iPnneq",
  "98": "2DnJjbjNTV9Nd5NOa1KGba",
  "102": "1djonDGMaLUqG4UD41P3iw",
  "104": "2SpEHTbUuebeLkgs9QB7Ue",
  "105": "6AbaUu4XtHu7pGkPE94Tat",
  "107": "70YvYr2hGlS01bKRIho1HM",
  "111": "0HOrDVS349XFcpCYsO2hAP",
  "112": "2OxkfL5jW8bvYTCNDLlRSY",
  "113": "40NRm1ZLvZpUSCUXAGGZ8J",
  "114": "5dXJ1SoksFkgdx3yxIoYNO",
  "115": "7e89621JPkKaeDSTQ3avtg",
  "117": "714hERk9U1W8FMYkoC83CO",
  "119": "4zGBAwjlJ0TP02mHH8Wpmo",
  "120": "3z8h0TU7ReDPLIbEnYhWZb",
  "122": "1uYyXXqWQJ0fBQ0a7iMU0a",
  "123": "0KMGxYKeUzK9wc5DZCt3HT",
  "124": "1hQFF33xi8ruavZNyovtUN",
  "125": "51qi5dgc9CsotM87GmRkAX",
  "126": "6y4FVJwf09ssxuRnlEgXkp",
  "127": "3DZ11M7LSpVQzYHnFx3i95",
  "129": "5jUA1njy3h6ynHLvPdEVHt",
  "130": "4mn7iv4DYJxPYbPy5R0nPE",
  "132": "1QEEqeFIZktqIpPI4jSVSF",
  "133": "1JQ6Xm1JrvHfvAqhl5pwaA",
  "134": "2pag2vElkdroT8hIO4Gozi",
  "135": "1BqnZOkYJbvYLOhN0qPJDm",
  "137": "4sf4Lq52b2iCoAgpge7a9g",
  "138": "77XlfkvXtMwppbEU5sku97",
  "139": "5gOd6zDC8vhlYjqbQdJVWP",
  "140": "5WI7WETcabzR2k2euhcpo7",
  "142": "7Kszjzps0xbQXyo1pO4KfE",
  "143": "0RnCUYXa7jhgTXtiMXF2PQ",
  "144": "5IMtdHjJ1OtkxbGe4zfUxQ",
  "145": "2HPB3px8MJZRMfu1L65Z41",
  "149": "3vkQ5DAB1qQMYO4Mr9zJN6",
  "150": "7D5ycpIrqwGNTQFKmzhDIg",
  "153": "3pbtBomO4Zt5gGiqsYeiBH",
  "155": "4o6BgsqLIBViaGVbx5rbRk",
  "156": "3K7Q9PHUWPTaknlbFPThn2",
  "161": "7HKez549fwJQDzx3zLjHKC",
  "162": "5vFFwU909VMZIBA7sZPtW0",
  "164": "3L7RtEcu1Hw3OXrpnthngx",
  "165": "0odIT9B9BvOCnXfS0e4lB5",
  "166": "2fuCquhmrzHpu5xcA1ci9x",
  "167": "1gzIbdFnGJ226LTl0Cn2SX",
  "168": "1mskmld5ZKEhRaNvYVPoqZ",
  "170": "28P5HAF0Kll9Xd9dX4qw7A",
  "172": "15Mh8m2BGTUptR8yy7fNAS",
  "173": "567EwOGPAXg7Y9DQZTEFEE",
  "175": "1TfqLAPs4K3s2rJMoCokcS",
  "177": "3XDeeP9wBZzGhIPZmLfEEx",
  "178": "3yDhZq8f17SmumVmEyCaRN",
  "179": "4ZhPLoMzZwewHLLjV1J15c",
  "180": "1JSTJqkT5qHq8MDJnJbRE1",
  "182": "6hci8n9UowepjRmCc6CKTv",
  "184": "1Qrdlkgg9I4J7r3P4kZNwr",
  "186": "1F43XlPBiwAUUIhrUGzylO",
  "187": "4S1VYqwfkLit9mKVY3MXoo",
  "188": "5vmRQ3zELMLUQPo2FLQ76x",
  "189": "54X78diSLoUDI3joC2bjMz",
  "190": "7FwBtcecmlpc1sLySPXeGE",
  "192": "7Ewz6bJ97vUqk5HdkvguFQ",
  "193": "7hkOgKKybgawYUcrkZD3wV",
  "194": "2GOGDZ9wAJbmznIstAxiU4",
  "195": "6HMFtoMvv6n6Q2eOyPFyne",
  "196": "1yg7fwwYmx9DQ2TdXUmfpJ",
  "197": "5zWZ9iNevP0397xB3jWV2z",
  "198": "4ZExvJvQXPEeYzGU0N3THi",
  "199": "0snPJPxkk0MbTc0xeUvAPt",
  "200": "7bkjJHsfX2rebJ3KZLegGt",
  "201": "798fUF6UnRn27xiVuKyJCi",
  "202": "1ukHtC2BBs51jmSGaxoEeL",
  "205": "7eafuv44YprITfOdzfVLoU",
  "206": "101m14qrjLJtXR4IwcXYv8",
  "208": "6C67KcwSOikGyrebYqgwjx",
  "211": "2DjWsDGgL1xNbhnr7f6t5F",
  "213": "58UEwo2r86awBBUSMZCP5X",
  "214": "7o2CTH4ctstm8TNelqjb51",
  "215": "4d6eqRtpDX7tydHJGDZUBQ",
  "216": "0kzSooCGpuphLwn8iTuO9h",
  "217": "1QRvbZIBvpQmoCyGNyaIwq",
  "219": "09huOVRryZNV2deKFZLJDC",
  "220": "4LFwNJWoj74Yd71fIr1W8x",
  "221": "7gSQv1OHpkIoAdUiRLdmI6",
  "222": "32gpJnMZkRafZdQvU7ZzR7",
  "224": "3J0AoQhAufniMrznCRJASD",
  "225": "1ZLgeJ8aUm1nJcddza8dVG",
  "226": "4OjJAGDDZTLlTNeOMBl7UM",
  "227": "3Cx4yrFaX8CeHwBMReOWXI",
  "228": "2v7ywbUzCgcVohHaKUcacV",
  "229": "21qnJAMtzC6S5SESuqQLEK",
  "230": "5PQQrMn2UOeO7I4Twy5HoZ",
  "231": "36rXHqN7D1ETFhyKXXKs4w",
  "232": "1fX0h6SaZBXwmr4haRvirQ",
  "233": "11d9oUiwHuYt216EFA2tiz",
  "234": "1L94M3KIu7QluZe63g64rv",
  "235": "7prFpeH9fXA7cL6ZZWLePs",
  "238": "4JGKZS7h4Qa16gOU3oNETV",
  "240": "3d9DChrdc6BOeFsbrZ3Is0",
  "242": "6pPWRBubXOBAHnjl5ZIujB",
  "243": "5iRPNyWioH9Km8gi58As4V",
  "244": "5wDSlUDuS3mVPq5TY25DZa",
  "245": "4JiEyzf0Md7KEFFGWDDdCr",
  "246": "7L93GESzq43UkKUt5FsOCq",
  "247": "2RsAajgo0g7bMCHxwH3Sk0",
  "249": "2LjiPAQOVazT8sRyXL3XRs",
  "250": "1oTHteQbmJw15rPxPVXUTv",
  "252": "1ohbjkuczl6hEoYEo931PH",
  "253": "0hrBpAOgrt8RXigk83LLNE",
  "255": "6PypGyiu0Y2lCDBN1XZEnP",
  "257": "4QZ6hp2CKRaZG5RI9zXQqg",
  "258": "2CdS3DRqWR5LAhy4hM5X9W",
  "260": "2rTYgHxgcndkUrRoU7x0Sv",
  "261": "5DiXcVovI0FcY2s0icWWUu",
  "262": "1Ic9pKxGSJGM0LKeqf6lGe",
  "263": "24LPjYUpC28ODnHNx25kqo",
  "265": "4UrgDocbHywDZv2f3mBhCq",
  "267": "7nYvUtkQMx1v80S2FH2s9J",
  "268": "1FkoVC85Ds3mFoK0fVqEqP",
  "270": "0oKOAL9nhFMieApXNLYkZ8",
  "271": "29fNIVCogo4jpvKgTtIwyb",
  "272": "7ygpwy2qP3NbrxVkHvUhXY",
  "273": "2lE7oRoKssULAtbWViL385",
  "274": "2fXKyAyPrEa24c6PJyqznF",
  "275": "3CiM7fBGbaP6jiyuH2Ot4j",
  "276": "2Pn5gvVioma5LHPxgEBBmD",
  "277": "0U9TKK9GYryei6Vn45TEdH",
  "280": "6vcdzohhBSbNdsZBh5IRpQ",
  "281": "3ptdPgclNeffhYA0aY1Nw7",
  "282": "79CUrU5o2KAVDTNm4x3eGU",
  "283": "0Gbz7QN5c8twO5YCZ9g1Kv",
  "284": "6MdqqkQ8sSC0WB4i8PyRuQ",
  "285": "7aQjPecQdIuNd1sz3KCDhD",
  "286": "3jDdpx9PMlfMBS5tOBHFm9",
  "287": "3vZO25GdYuqFrR1kzZADnp",
  "289": "0KligwQn4Iy344p2Q5m6k6",
  "292": "1aJnGme5ZRltYTp8FJ52eZ",
  "295": "4ACxa9buEUnOdYEoPcnMpi",
  "297": "2i4AouhQeGFBb4g3cx8yqg",
  "298": "7jxGRU3EH0QveYx4bD32i7",
  "299": "5WTPhYmwwojFP73O7p3Izi",
  "303": "1OxcIUqVmVYxT6427tbhDW",
  "305": "0SLtqCrXBRrnkxSOMA3X4W",
  "306": "1H5VQuShs4qfwBXyHF0PeH",
  "307": "1NcvMCA0sT05KwneYsD2TY",
  "308": "4rvT5iZVOCJeXZrDvy6JFK",
  "309": "6Qyc6fS4DsZjB2mRW9DsQs",
  "310": "00i2HU7TEzzftShjRrDSEF",
  "311": "1Cwsd5xI8CajJz795oy4XF",
  "312": "31bf9SEOppLU6lQ85d8om6",
  "315": "3JfkNCiXjHEVkbFfCQ417E",
  "316": "1XPcnAQncIro2b4sKDdDnX",
  "317": "7t86fVeDAd63ThaR0ZkxXS",
  "319": "5OQsiBsky2k2kDKy2bX2eT",
  "321": "503OTo2dSqe7qk76rgsbep",
  "323": "63nkNgHkmfgjElTEnCzKYU",
  "324": "1hEh8Hc9lBAFWUghHBsCel",
  "325": "1vlTMKVV0FxG6CxGTmSY3t",
  "326": "49X0LAl6faAusYq02PRAY6",
  "328": "4BggEwLhGfrbrl7JBhC8EC",
  "329": "3Fzlg5r1IjhLk2qRw667od",
  "330": "2Uy6EhQXAYkXA6MohPgjpV",
  "331": "0I3q5fE6wg7LIfHGngUTnV",
  "332": "6FLwmdmW77N1Pxb1aWsZmO",
  "333": "0kuLj2Y2tq3ygMfnv0LDe3",
  "335": "0EoGXXi91KSqAIY7SSgizW",
  "339": "3aw9iWUQ3VrPQltgwvN9Xu",
  "341": "2Za2mUwmQoSxWPscaY2vxl",
  "343": "4w1lzcaoZ1IC2K5TwjalRP",
  "344": "4anDsZBavxjw3Ktw6ICGYd",
  "345": "3fHw1Y4sD4U2b0s3K4ql9I",
  "346": "0b9djfiuDIMw1zKH6gV74g",
  "347": "5P2hEcHjoNMh33EsFPPOJE",
  "348": "2kvg4AwMIstkygdQhfFfSf",
  "349": "4yOU9FaCmFFo2qfy1FHIe3",
  "350": "1qzHqfvKrZWo6dVHM1dXrj",
  "353": "0xmjwnQ3FNE6HuWCt2nHdZ",
  "354": "1Z3V1fGR5HYr232lLPVD9G",
  "356": "2nLtzopw4rPReszdYBJU6h",
  "357": "3CpoeW0cZSDzIRv5z34F87",
  "358": "2PpruBYCo4H7WOBJ7Q2EwM",
  "359": "0JDp7p99FSja52T0YBLupR",
  "360": "7iL6o9tox1zgHpKUfh9vuC",
  "361": "4zA30wJPvNvQ3WjB8jtGaF",
  "363": "09JkIMWSVYi143LoWnY1fa",
  "364": "1SKPmfSYaPsETbRHaiA18G",
  "366": "0bWKniFVup1UYgoZww89Vp",
  "367": "7dyluIqv7QYVTXXZiMWPHW",
  "368": "71Sw32dLcwyiRvp3dCA8ZH",
  "369": "1AETk3EwqrgVaMwlaLblfh",
  "370": "1xNcBAoUw8Hz6LqK2jt4Ff",
  "371": "4wzt5Rrk3W98pHXAqutuJw",
  "373": "0Gsj2iZerDbXbU0G1IHuB2",
  "376": "6FlAGda9qkDhTU7ctFM4uG",
  "377": "1c0zagykmGPDYuxJeDqZhJ",
  "378": "5imShWWzwqfAJ9gXFpGAQh",
  "379": "1qEHgdFqUxFebMPk8s2HLY",
  "381": "71LzkFemz0B8nmk8LcFyUg",
  "382": "2nGFzvICaeEWjIrBrL2RAx",
  "383": "5xv4ggemGPNpowZAMwEYHH",
  "384": "2T3jgoAMbBXiMMD8pSc6QL",
  "385": "2SDx0PooHZI1SQKR0y44bs",
  "387": "66Bzmhj4cOinK5bxjx5DAK",
  "388": "0ouVaMksipfBTcN5J95Gj0",
  "390": "4WZYBWngq9ODEqPB05WW7S",
  "391": "06hsdMbBxWGqBO0TV0Zrkf",
  "392": "57RHMnLMQx8Qz5V6c0E8dF",
  "395": "1zusIxNqJu8i4g6P6hJ2Qa",
  "396": "2uun7r1VosRzqTQZmffCu6",
  "397": "5R8dQOPq8haW94K7mgERlO",
  "398": "5wznxkB792LjSRdbZ1J1zo",
  "399": "5VGlqQANWDKJFl0MBG3sg2",
  "400": "3DamFFqW32WihKkTVlwTYQ",
  "401": "0fPf9CDFzVnHpcfld5XVtO",
  "403": "3B1dszUJvlEpVbzTHIlLxv",
  "405": "2b712q3E27nyW6LGsZxr0y",
  "406": "1gv4xPanImH17bKZ9rOveR",
  "407": "6sjGsKuInpaK3uoaWGe22W",
  "410": "386RUes7n1uM1yfzgeUuwp",
  "411": "7nqlRkgNyEpb9nvb03GMp7",
  "412": "4VRLGNMTfymoYzD4dLAsNb",
  "414": "3bidbhpOYeV4knp8AIu8Xn",
  "416": "0HqeTDZMGlYDmgGGVFQrSg",
  "417": "3di5hcvxxciiqwMH1jarhY",
  "419": "27ilMN1oiW9849fReEYgOj",
  "421": "1xN7BpTAWnZkuSLOtRP6Qc",
  "422": "3U4isOIWM3VvDubwSI3y7a",
  "423": "423RKXolCbgBbkF8WanOwA",
  "424": "60nZcImufyMA1MKQY3dcCH",
  "425": "70LrxJ5u19umvrXbC19g20",
  "426": "2Foc5Q5nqNiosCNqttzHof",
  "427": "2vwlzO0Qp8kfEtzTsCXfyE",
  "428": "2dLLR6qlu5UJ5gk0dKz0h3",
  "430": "0nrRP2bk19rLc0orkWPQk2",
  "431": "2ixsaeFioXJmMgkkbd4uj1",
  "432": "18AJRdgUoO9EYn11N7xzaT",
  "433": "7vFoFDWqTX0mHzLfrF1Cfy",
  "435": "0ifSeVGUr7py5GggttDhXw",
  "437": "4VrWlk8IQxevMvERoX08iC",
  "438": "4kbj5MwxO1bq9wjT5g9HaA",
  "439": "2YYt1dJwu99XCVwH8yyOPR",
  "440": "2RfM3MKoo4BHWTAQsfXRSo",
  "441": "6hmhG1b4LEyNuashVvuIAo",
  "442": "1Yk0cQdMLx5RzzFTYwmuld",
  "445": "7LMtp4HBhWLQ2P2POPn6li",
  "446": "23pZgY01lBlbwGyLIqZHt1",
  "447": "41Fflg7qHiVOD6dEPvsCzO",
  "448": "78TTtXnFQPzwqlbtbwqN0y",
  "452": "2FnUyLhe7sjXgnZlK9sc0z",
  "453": "1zB4vmk8tFRmM9UULNzbLB",
  "454": "7qiZfU4dY1lWllzX7mPBI3",
  "456": "3bWAqKDWg6u1davspr5IkS",
  "457": "6QgjcU0zLnzq5OrUoSZ3OK",
  "458": "08bNPGLD8AhKpnnERrAc6G",
  "461": "09IStsImFySgyp0pIQdqAc",
  "462": "6QfS2wq5sSC1xAJCQsTSlj",
  "463": "2qT1uLXPVPzGgFOx4jtEuo",
  "464": "5Xc9L411IGVexidbaF7CHG",
  "466": "0F7FA14euOIX8KcbEturGH",
  "468": "2lWIShFroC58eaaU77tmjA",
  "469": "0TK2YIli7K1leLovkQiNik",
  "472": "4NB5xE2cE0Hf8cGnzSiWM7",
  "473": "5iLoVWRuwPity9CuN1VTJ8",
  "474": "6AVErIh5UwMFMXc29iij9L",
  "475": "7K0Jghh9by2jPjU0IuA1r6",
  "476": "4JgBDkPPhe01Dy9hOeJQEm",
  "477": "6Ac4NVYYl2U73QiTt11ZKd",
  "478": "6Fba9RZtC6vTY814JToDtP",
  "479": "3SnGymj6ijE2iuUfWxLo1q",
  "480": "127QTOFJsJQp5LbJbu3A1y",
  "481": "29nwG4y9NFmN76yfUfc01d",
  "482": "6qYkmqFsXbj8CQjAdbYz07",
  "483": "7d3cKDG22Ig9kZOS1qsq3S",
  "484": "4k5FeWIdUaBx5OZdvrSYP1",
  "485": "2G0GextMwZJLkNxcSZ7ZJ3",
  "486": "1ChulFMnwxoD74Me8eX2TU",
  "488": "3jjujdWJ72nww5eGnfs2E7",
  "489": "1mCsF9Tw4AkIZOjvZbZZdT",
  "490": "6L89mwZXSOwYl76YXfX13s",
  "491": "0ofMkI3jzmGCElAOgOLeo3",
  "493": "15mZo1Kah03g8CTLbSsWrr",
  "495": "5NwkWwfRJaT55hEPtCmJHx",
  "497": "48Ej1CDmpsETlImicgiXWC",
  "498": "5fgkjhICZnqFctrV0AyuQD",
  "499": "0qxYx4F3vm1AOnfux6dDxP",
  "501": "6ek9SiEj5a65WIs2EV7qiM",
  "502": "3fH4KjXFYMmljxrcGrbPj9",
  "503": "4QlzkaRHtU8gAdwqjWmO8n",
  "504": "6apPqjW8ezpKEicAkkBlvO",
  "505": "5pKJtX4wBeby9qIfFhyOJj",
  "507": "7idTMG6EKZy0531lIx8RJ5",
  "508": "7GIxdonjm1JVjdxiTxL6Ja",
  "509": "5M2y8QdDepGYMsWyxhoxQU",
  "510": "2tUBqZG2AbRi7Q0BIrVrEj",
  "511": "5UqCQaDshqbIk3pkhy4Pjg",
  "512": "5ZULALImTm80tzUbYQYM9d",
  "515": "0gQtd0FQjuJSsuK2qHFYoF",
  "518": "2gam98EZKrF9XuOkU13ApN",
  "520": "6naxalmIoLFWR0siv8dnQQ",
  "521": "0BxfFnk0YzONqvmrkO0QrB",
  "523": "0eqH0ALoDQevq59YcQ53KE",
  "524": "7qtAgn9mwxygsPOsUDVRRt",
  "525": "36482hNESSwELpr9sS3NbE",
  "526": "3EDS89HeAhHiZKlljciK0a",
  "527": "2goLsvvODILDzeeiT4dAoR",
  "528": "53Za5vyGc1x7GxgJVRjRKc",
  "529": "1wfzOH54LylpiG8hAOjKcS",
  "530": "7s25THrKz86DM225dOYwnr",
  "531": "4H1iMlEWKZmpKTHCZzDhju",
  "532": "4Hhv2vrOTy89HFRcjU3QOx",
  "533": "5IVuqXILoxVWvWEPm82Jxr",
  "534": "5TAf4lnZCZTLlZHNZMLFLi",
  "535": "0FbbqjDqBNa78SL76JfCfX",
  "536": "77XwQEPxhY65b8rPszET9u",
  "537": "1kdxZYbXrqBX2hWtw3VFQF",
  "538": "3cbV252akVZInSvJk7jAYX",
  "539": "6HSXNV0b4M4cLJ7ljgVVeh",
  "540": "2aI21FnmY7TJVKeMaoQZ0t",
  "541": "6qspW4YKycviDFjHBOaqUY",
  "542": "7H8zey5My6uNdD2TxeCb9F",
  "543": "2GbePPrWWSRxcmW6QRSPae",
  "544": "1Jaah2tmN9Hv81A87KZ1MU",
  "545": "39q7xibBdRboeMKUbZEB6g",
  "546": "1mXuMM6zjPgjL4asbBsgnt",
  "548": "3xrn9i8zhNZsTtcoWgQEAd",
  "549": "0gJvqi9QyASOCtJu99tytc",
  "550": "21jGcNKet2qwijlDFuPiPb",
  "551": "0e7ipj03S05BNilyu5bRzt",
  "552": "2srTtSrzY4n10C7abVTrBm",
  "553": "5IKLwqBQG6KU6MP2zP80Nu",
  "554": "4GhtDORJiSRYxj6M1bv0vX",
  "555": "1MntHPLU1T7a9W4tojbg8g",
  "556": "1umFfZGw8bsBd1a0fLTQI3",
  "558": "4ZoffM8qkSNg9uwLq3DQY7",
  "559": "2MAVcVr2oylw2OZ3hojWYj",
  "560": "5QpaGzWp0hwB5faV8dkbAz",
  "561": "2Cd9iWfcOpGDHLz6tVA3G4",
  "562": "7mze3mJmu79AJu8SnS37pS",
  "563": "2c3sKqWYVJ0NsE3elgRhKH",
  "564": "2EM9zpAc7PVeoAydmbfVIL",
  "566": "7v02Sn9vYRQ6pc1lqhnkWY",
  "567": "4RADreHMvMkZwsPgPr9z5c",
  "570": "4KoecuyOpZaNFZ0UqVsllc",
  "571": "2zCWIYloMDa6Bs3K5v78sk",
  "573": "1p5kC161fWMA2QlwV3Vi4W",
  "574": "0gmbgwZ8iqyMPmXefof8Yf",
  "575": "3N4DI1vuTSX1tz7fa2NQZw",
  "576": "4BfRDZLIiznSnwU7DdDL9N",
  "577": "25FTMokYEbEWHEdss5JLZS",
  "578": "7wZUrN8oemZfsEd1CGkbXE",
  "579": "583xVl0Sbj93uU4ceixgU8",
  "580": "4bHsxqR3GMrXTxEPLuK5ue",
  "581": "5LYJ631w9ps5h9tdvac7yP",
  "582": "4ePP9So5xRzspjLFVVbj90",
  "583": "2374M0fQpWi3dLnB54qaLX",
  "585": "7zLGHdfJ3JRPxvc96mEPEi",
  "586": "41OIyMJsSFMjdjZjL4tHEx",
  "587": "7G7tgVYORlDuVprcYHuFJh",
  "588": "2TIlqbIneP0ZY1O0EzYLlc",
  "589": "5fVZC9GiM4e8vu99W0Xf6J",
  "590": "017PF4Q3l4DBUiWoXk4OWT",
  "592": "4oDZ5L8izBals6jKBJDBcX",
  "593": "6b2oQwSGFkzsMtQruIWm2p",
  "594": "7mnGQesk1TzQLzQ9bYWZPR",
  "595": "2lnzGkdtDj5mtlcOW2yRtG",
  "599": "0ARK753YaiJbpLUk7z5yIM",
  "601": "1xNmF1Uep5OGutizZSbKvd",
  "602": "7JKEA8xYDoFp4q0QBW2PGg",
  "603": "46q5BtHso0ECuTKeq70ZhW",
  "604": "4c6vZqYHFur11FbWATIJ9P",
  "607": "3RjyVvrqmS26Sq6vUMswWd",
  "608": "6ECp64rv50XVz93WvxXMGF",
  "609": "6liaHE9iHh23PLVvw7lK8V",
  "610": "1YGZyfvdgZxzipWoWYVKxi",
  "612": "0azC730Exh71aQlOt9Zj3y",
  "614": "5uCax9HTNlzGybIStD3vDh",
  "615": "4hrae8atte6cRlSC9a7VCO",
  "617": "1er4mjSaS1VGfMp23rzsCV",
  "618": "1yy2DlSDtEt90d54rPDPXz",
  "619": "6Nq5lE0CeOAAAqN4qhkbZU",
  "620": "7ByhqIL2dqk4W0jPTkWc9A",
  "621": "6FRtjadDsEhZIQIlh1loEM",
  "622": "6ZLGthToczpvnL5Eoy6yrY",
  "623": "0bfvHnWWOeU1U5XeKyVLbW",
  "627": "1eyq8cjUQ2daFthW2PC2GM",
  "630": "0COqiPhxzoWICwFCS4eZcp",
  "631": "1fr92Vupmcs2vgLMFVQ7rd",
  "633": "77loZpT5Y5PRP1S451P9Yz",
  "635": "2JzZzZUQj3Qff7wapcbKjc",
  "637": "0fYVliAYKHuPmECRs1pbRf",
  "639": "3RlsVPIIs5KFhLFhxZ4iDF",
  "641": "3WkibOpDF7cQ5xntM1epyf",
  "645": "78TVWUTtCC4WAhi0SRPxQK",
  "653": "7tqhbajSfrz2F7E1Z75ASX",
  "654": "4NRQwaks9r58tTDvr4iEyv",
  "655": "63xdwScd1Ai1GigAwQxE8y",
  "657": "3SdTKo2uVsxFblQjpScoHy",
  "658": "5YLnfy7R2kueN0BRPkjiEG",
  "659": "3zBhihYUHBmGd2bcQIobrF",
  "660": "7sqK6f8dHVx3Q1GjFrVyGl",
  "661": "2QbSGkb3TgghEHpjKCsznm",
  "663": "5uES1C2NgkdrNHiCwf9jRr",
  "664": "3VgrSJEKBRT3xmwzpaxxEF",
  "665": "4JLcAU2xY90qTkTSNM1lUa",
  "667": "2nwCO1PqpvyoFIvq3Vrj8N",
  "668": "0ZQ6ckgerHYM5mOUxTl99Q",
  "670": "1tqT6DhmsrtQgyCKUwotiw",
  "672": "77Nw4E8ji9K2vG23rQikBc",
  "674": "6Rqn2GFlmvmV4w9Ala0I1e",
  "675": "3mRM4NM8iO7UBqrSigCQFH",
  "676": "3qiyyUfYe7CRYLucrPmulD",
  "678": "7zkLpY72g6lKQbiHDqri1S",
  "679": "5KqldkCunQ2rWxruMEtGh0",
  "681": "1qCQTy0fTXerET4x8VHyr9",
  "682": "0wokCRaKD0zPNhMRXAgVsr",
  "684": "6qUEOWqOzu1rLPUPQ1ECpx",
  "686": "3y8pywLbRGC1x8oCDeTMyL",
  "687": "2oWMI54r0qT4N8Xb4C76vq",
  "688": "3KDLyp0cMrWeEZI1PTHYm5",
  "690": "2fARVTvENb670WbTS57RqU",
  "695": "2kQLJexCx8wPTAqK0x0ijO",
  "696": "2avKuMN2QXkaG9vvHa2JLt",
  "698": "3SFXsFpeGmBTtQvKiwYMDA",
  "699": "3Mmt6Xk0H6VR92PEp6x3hP",
  "700": "6VoIBz0VhCyz7OdEoRYDiA",
  "703": "5Hroj5K7vLpIG4FNCRIjbP",
  "704": "7o7E1nrHWncYY7PY94gCiX",
  "707": "5b7OgznPJJr1vHNYGyvxau",
  "710": "0UOxp1BpnD8uPQMKU4wKjz",
  "713": "6QLspHLCLftSGPa6vNzKuo",
  "726": "1Q1b8eVkUPGlpSArl8JAVw",
  "728": "6RtPijgfPKROxEzTHNRiDp",
  "731": "5vYA1mW9g2Coh1HUFUSmlb",
  "732": "2vlgOAH3M8Fmo19wOjeRyw",
  "733": "2hKdd3qO7cWr2Jo0Bcs0MA",
  "738": "2m1hi0nfMR9vdGC8UcrnwU",
  "739": "1arJHhz6TxMV50SNvSmGnV",
  "741": "0DaOFUhUEc416QdUaW9paE",
  "743": "4Y6cDd4EPHcEbiUKdyvNwM",
  "744": "3ypMsqUwfNFMiooMLVHfkp",
  "745": "5fRvePkRGdpn2nKacG7I6d",
  "747": "0WGn8xhpPumX73lECUY5Yo",
  "748": "3QRM0qZB7oMYavveH0iEqx",
  "749": "3cfOd4CMv2snFaKAnMdnvK",
  "750": "7kyMLaXepcGHIrsLqoiTB8",
  "751": "1SssFw74DdHVjRa6ADggdD",
  "752": "7lQWRAjyhTpCWFC0jmclT4",
  "754": "7FkyQsWH9mmxoYLCNj4f8y",
  "755": "6Sy9BUbgFse0n0LPA5lwy5",
  "757": "6X6ljHP0LlsdUILsGwfQ40",
  "758": "4V9BTST4BSkvOL4xIQNHuS",
  "760": "4POgt5ayni68MeLqclubcC",
  "761": "4hObp5bmIJ3PP3cKA9K9GY",
  "762": "0qi4b1l0eT3jpzeNHeFXDT",
  "764": "6mHOcVtsHLMuesJkswc0GZ",
  "765": "3yrSvpt2l1xhsV9Em88Pul",
  "766": "5jWI1xNxABzDRFTnD2yp8L",
  "767": "1k1Bqnv2R0uJXQN4u6LKYt",
  "768": "6iXQrhhgBisdfvS34EMTZ3",
  "769": "1eOJAiCKFuMda0fPRvjcuc",
  "770": "3vjQt1znaFEnX3PBXsgtVc",
  "771": "1i1OuCNhNf7JwrlWlFZFu1",
  "772": "1K3LRUEcUz5FMtPYyg0F45",
  "773": "0D2VYiRlBv43asKUgieZaM",
  "775": "3ydfhgIZIc2j39NLIhpJpq",
  "776": "4XPWKmy05Rcff6TLHNoNF8",
  "778": "46xkXPGjR9Ig9BcaTUNus3",
  "779": "05p7wWoGLZIhU0xqWnc9rJ",
  "780": "2LEF1A8DOZ9wRYikWgVlZ8",
  "781": "4650WGL6InVqP7YN5POqIz",
  "782": "0iOZM63lendWRTTeKhZBSC",
  "783": "1jcPcDu2YawPfLhwjYnqK2",
  "784": "18DfMhEx4ddoreHrvZDF6Q",
  "786": "07q0QVgO56EorrSGHC48y3",
  "791": "03UrZgTINDqvnUMbbIMhql",
  "792": "3AeicLnm55RqcXGBKYQolM",
  "793": "6F5c58TMEs1byxUstkzVeM",
  "794": "0pMUR7Uvp6vxlbG0qBFvgM",
  "795": "7jGzYUZ2Bgg8BDfYlQRfn8",
  "798": "2Qm5DrmotzWvqNM3JlcQYo",
  "800": "5MoDQWMDMaAGDEiWsJfeCi",
  "802": "7o9uu2GDtVDr9nsR7ZRN73",
  "803": "0IWtEFQBwRHaMXZQtGEVcM",
  "804": "36EWx5B78n8sSfpmtKrUUV",
  "806": "1JLn8RhQzHz3qDqsChcmBl",
  "808": "3iMLRCGHLQ135LtMjKLkO8",
  "809": "6N7gPTru90HYLRUIVDQ185",
  "811": "1pTGc8pwyo6xtgXBKCBcFn",
  "812": "0XvjOhwCnXXFOSlBbV9jPN",
  "815": "5CQ30WqJwcep0pYcV4AMNc",
  "816": "7rPzEczIS574IgPaiPieS3",
  "819": "57bgtoPSgt236HzfBOd8kj",
  "825": "37ZJ0p5Jm13JPevGcx4SkF",
  "828": "2pX4FpOgwItRVPPUFdRcxA",
  "829": "567UAkWoLBqZ709s3Qcbze",
  "830": "7xe3EQCvXnx6Q0zs41Y65n",
  "833": "4fHDlIntTsRGSyTg5UYZYC",
  "834": "3aPlQWU07jGgyHaBHVS5TS",
  "841": "27AHAtAirQapVldIm4c9ZX",
  "842": "5Klo65Y9uouLjNVDV3pqh7",
  "848": "1GeNWyZtCHbcp3ZWp8GTOO",
  "849": "2lFFiNm0XtgJ6wkdncTB4k",
  "852": "0CsM8VGDi38kusMv3pxyj1",
  "854": "5XcZRgJv3zMhTqCyESjQrF",
  "856": "1UzofFX5AkfTDnwjcBkM4J",
  "857": "1hlveB9M6ijHZRbzZ2teyh",
  "860": "5yGTQzYbEdY6B9RFZJypgt",
  "862": "28UMiBhn383n9S7GL4tsxD",
  "863": "0GONea6G2XdnHWjNZd6zt3",
  "864": "6uJrLZzBxS4JewGnihjNzM",
  "865": "4gvea7UlDkAvsJBPZAd4oB",
  "867": "3Nf8oGn1okobzjDcFCvT6n",
  "868": "6YrHQ3Uv9YXK2gJNVTlT8P",
  "869": "5Nm9ERjJZ5oyfXZTECKmRt",
  "871": "25sgk305KZfyuqVBQIahim",
  "872": "6RUKPb4LETWmmr3iAEQktW",
  "873": "5qrSlOut2rNAWv3ubArkNy",
  "874": "0qOnSQQF0yzuPWsXrQ9paz",
  "875": "3ebXMykcMXOcLeJ9xZ17XH",
  "876": "1hRFVIy9As8OVRk8B7CrD5",
  "882": "3Zh5cecN8TqelTN30SJUww",
  "883": "22HYEJveCvykVDHDiEEmjZ",
  "884": "392zwJVuiuhDZC3ShNmLkD",
  "886": "0reKGVcWLVvl1FzjZ6TACy",
  "887": "3NvS0SxNWIPiAJoPWUpZzr",
  "892": "0jWgAnTrNZmOGmqgvHhZEm",
  "893": "4DX82Vc8qAH4jJPvKxvwg6",
  "894": "3S0OXQeoh0w6AY8WQVckRW",
  "895": "5TmFTHZp7HjBXjjsFvCY6h",
  "896": "2YdX7PEziOImkySNDWsaKM",
  "897": "13P5rwmk2EsoFRIz9UCeh9",
  "898": "1jJci4qxiYcOHhQR247rEU",
  "899": "3qqho4PnTn3zlMPBzWhFFD",
  "900": "7dwJqwTXDtsrX1QLqb0o96",
  "901": "4pW3aTX3kAmOaPJfc9UM12",
  "905": "15BQ7vEDv2LJuh8TxWIhtd",
  "907": "6brl7bwOHmGFkNw3MBqssT",
  "908": "2aBxt229cbLDOvtL7Xbb9x",
  "914": "2Fxmhks0bxGSBdJ92vM42m",
  "915": "70ludZZEUJy1aFVkPI0Kpi",
  "917": "7w87IxuO7BDcJ3YUqCyMTT",
  "920": "6zsk6uF3MxfIeHPlubKBvR",
  "924": "5rb9QrpfcKFHM1EUbSIurX",
  "925": "4UDaVq5tm2mQ6tNgWydhUX",
  "926": "3MrWxJaD2AT0W9DjWF64Vm",
  "931": "4fazGt0v2v2zkzddQOcDZD",
  "933": "0Pvo0X51jIUXjC6tH4OO36",
  "936": "2YWjW3wwQIBLNhxWKBQd16",
  "937": "7eJMfftS33KTjuF7lTsMCx",
  "938": "1ue7zm5TVVvmoQV8lK6K2H",
  "942": "4POyHI0icFZTLfXLMNEw1s",
  "951": "42et6fnHCw1HIPSrdPprMl",
  "954": "42ydLwx4i5V49RXHOozJZq",
  "957": "6FE2iI43OZnszFLuLtvvmg",
  "959": "2nx86MrPkXWQctveAEFJBf",
  "961": "51tUT1gHE30GQPhn1agudM",
  "962": "3E7ZwUMJFqpsDOJzEkBrQ7",
  "965": "1lkvpmrCaXK8QtliFDcHBO",
  "967": "3ZI3sK9ZJB3LOiZtCs9l3p",
  "969": "6lc1Rq31ILjpydczoURQPb",
  "970": "1ifq3DVpguU02W6Prh5T3u",
  "973": "7EQGXaVSyEDsCWKmUcfpLk",
  "974": "7DFNE7NO0raLIUbgzY2rzm",
  "975": "6Z8R6UsFuGXGtiIxiD8ISb",
  "976": "04aAxqtGp5pv12UXAg4pkq",
  "977": "01v2iOCnr4HDb1nUJLZods",
  "978": "0aBKFfdyOD1Ttvgv0cfjjJ",
  "979": "0b9oOr2ZgvyQu88wzixux9",
  "980": "21BYhl07wWqGRQaj7sUxdV",
  "982": "1rqqCSm0Qe4I9rUvWncaom",
  "985": "4wtHbIS26FOtpjMkaQQ8Zk",
  "988": "4jh9olf0OKCokpzxSyLeJx",
  "990": "01AfqEDao4dHz4bjpTVgsz",
  "992": "4SNJqELEbMqGWydQQMycco",
  "1003": "3YKptz29AsOlm7WAVnztBh",
  "1007": "1qj8Td79dgmLqCYafkhQ3G",
  "1010": "31qCy5ZaophVA81wtlwLc4",
  "1011": "7lPN2DXiMsVn7XUKtOW1CS",
  "1012": "6b37xrsNCWYIUphFBazqD6",
  "1013": "3KyKxJ4P3pVCgaZwaq2rUC",
  "1014": "4iJyoBOLtHqaGxP12qzhQI",
  "1015": "3dkIE8P7hvl3tHl9KSb6dA",
  "1017": "4GUvOaJiYlvFTKXDEg3QR6",
  "1020": "3evG0BIqEFMMP7lVJh1cSf",
  "1021": "3rmo8F54jFF8OgYsqTxm5d",
  "1022": "6zSpb8dQRaw0M1dK8PBwQz",
  "1023": "4Dvkj6JhhA12EX05fT7y2e",
  "1024": "75FEaRjZTKLhTrFGsfMUXR",
  "1025": "62MosvjGMQY3HeGPFEsmM1",
  "1026": "1rDQ4oMwGJI7B4tovsBOxc",
  "1027": "3ia3dJETSOllPsv3LJkE35",
  "1028": "3MrRksHupTVEQ7YbA0FsZK",
  "1029": "1PuU1oIYtIaPHF0ogxWMvc",
  "1030": "1CtAzw53AIXKjAemxy4b1j",
  "1031": "6ADSaE87h8Y3lccZlBJdXH",
  "1032": "36orMWv2PgvnzXsd5CJ0yL",
  "1033": "2V65y3PX4DkRhy1djlxd9p",
  "1036": "1yU51sZHtxvZHlni32lgxM",
  "1038": "3zgJHNEorjbLLThp6TiMhz",
  "1039": "58X2vGyNWT2ZPEaGUw1tAb",
  "1040": "5v55pDsyrxIs6OTk3E5l69",
  "1041": "4SS4YfDAEQG0fZAe1xfgn3",
  "1042": "7bVwUOySQGO2afJ0LArAMi",
  "1043": "3No0idjeViPyWDP4gh1YGo",
  "1044": "0FSlaiuv4eBrrjz05jpxz6",
  "1045": "1ijNH4JCOlLJz7ToxmjUeY",
  "1046": "0YWmrHLItfjD7pJ8NzlXke",
  "1047": "2qkma39oRZ0rzGkyE2gdHd",
  "1048": "1uINDFsUumg9C2Ob5dgi0v",
  "1049": "52vLuv7YSkhX27eMg4wv2L",
  "1051": "4GgAm1IIj5mIUsA8ucKA0k",
  "1052": "0xljZqZHvXhVfse33fQ9bK",
  "1053": "5Ls1Ir6Vl5frICvnH4nVRH",
  "1054": "76FeIWgiIFG9v1AigsbWbj",
  "1055": "4Dmlg5FYyHRYipiIqXJ2fa",
  "1056": "3JO3ywp8UufIiKkszm7DkE",
  "1058": "3uhF5EBcuqqXELlszBhIOy",
  "1059": "1BBIW3lDfwK9PXOFOedZmo",
  "1060": "1mvZErZBp7WZT3HfGBykao",
  "1061": "4Cz2101t2TdPKBsgb7O6dS",
  "1062": "5MhsZlmKJG6X5kTHkdwC4B",
  "1063": "3SjXx3rbNGk8nCho8YEoz5",
  "1064": "3o1ZHdEdRaMhbGwpwnJTv8",
  "1065": "71CFZjdSm2WSh5S6TPd69A",
  "1066": "4pItP9yMHJ4Klk8U6eOmLx",
  "1067": "2Gd0oV24QsH0zb9nKFx7s5",
  "1068": "6tCLQ3LO1V9l6qdrrwdV6q",
  "1069": "3qChO81Z9r3KDyIj4w1m4T",
  "1070": "4q5ALFIbrkLni1fM3j5ioA",
  "1071": "6HXZ1iAfFjWH8QPuqt71oo",
  "1072": "7r0GgmwNre1NtsrRA00bMa",
  "1073": "16u7VaQftmMu4ciA011z9X",
  "1074": "3gFmdwuELZGrSCghc3CWWr",
  "1075": "7M9llL9G2Ei3OjwXAc6R58",
  "1076": "1d8oE2UouwTNZ0AYcnpwqQ",
  "1077": "5QFDqIgiyNkCiUVLM40CkD",
  "1078": "16RIvwKqIibSQbamiVyxAo",
  "1079": "7teMwabPGrZwzqCEfdxVYx",
  "1080": "2xSnGBBEUuoKJAbLBtuxDr"
}
